exchange/__init__.py
exchange/app.py
exchange/services.py
test/fixtures/__init__.py
exchange_rates_last_hm_alex-0.0.2.dist-info/METADATA
exchange_rates_last_hm_alex-0.0.2.dist-info/WHEEL
exchange_rates_last_hm_alex-0.0.2.dist-info/top_level.txt
exchange_rates_last_hm_alex-0.0.2.dist-info/RECORD
