Metadata-Version: 2.1
Name: exchange-rates-last-hm-alex
Version: 0.0.2
Summary: Exchange rates getter
Home-page: https://gitlab.com/ExampleUserForYandex/last
Author: BiggiPiggi
Author-email: aszmey.war@gmail.com
License: UNKNOWN
Platform: UNKNOWN
Classifier: Programming Language :: Python :: 3
Classifier: Operating System :: OS Independent
Requires-Python: >=3.7
Requires-Dist: aiohttp (==3.6.2)
Requires-Dist: aiomisc
Requires-Dist: aiomisc-dependency
